LICENSE
MANIFEST.in
README.rst
setup.py
buildbot_pipeline/__init__.py
buildbot_pipeline/build.py
buildbot_pipeline/builder.py
buildbot_pipeline/changes.py
buildbot_pipeline/file_store.py
buildbot_pipeline/filters.py
buildbot_pipeline/fixprops.py
buildbot_pipeline/junit.py
buildbot_pipeline/monkey.py
buildbot_pipeline/reporters.py
buildbot_pipeline/schedulers.py
buildbot_pipeline/steps.py
buildbot_pipeline/utils.py
buildbot_pipeline.egg-info/PKG-INFO
buildbot_pipeline.egg-info/SOURCES.txt
buildbot_pipeline.egg-info/dependency_links.txt
buildbot_pipeline.egg-info/entry_points.txt
buildbot_pipeline.egg-info/not-zip-safe
buildbot_pipeline.egg-info/requires.txt
buildbot_pipeline.egg-info/top_level.txt
buildbot_pipeline/web/__init__.py
buildbot_pipeline/web/dist/favicon.ico
buildbot_pipeline/web/dist/index.html
buildbot_pipeline/web/dist/assets/index.05cf54d1.js
buildbot_pipeline/web/dist/assets/index.70f8dc91.css